MANIFEST.in
README.md
requirements.txt
setup.cfg
setup.py
SNSNotifications/__init__.py
SNSNotifications/channel_manager.py
SNSNotifications/types.py
SNSNotifications.egg-info/PKG-INFO
SNSNotifications.egg-info/SOURCES.txt
SNSNotifications.egg-info/dependency_links.txt
SNSNotifications.egg-info/requires.txt
SNSNotifications.egg-info/top_level.txt
SNSNotifications/channels/__init__.py
SNSNotifications/channels/mail/__init__.py
SNSNotifications/channels/mail/mailable.py
SNSNotifications/channels/mail/transport.py
SNSNotifications/channels/mail/transport_manager.py
SNSNotifications/channels/mail/transports/__init__.py
SNSNotifications/channels/mail/transports/smtp.py
SNSNotifications/channels/slack/__init__.py
SNSNotifications/channels/slack/message.py
SNSNotifications/mixins/__init__.py
SNSNotifications/mixins/template.py